LICENSE
MANIFEST.in
README.md
setup.py
gita/__init__.py
gita/__main__.py
gita/cmds.json
gita/common.py
gita/info.py
gita/io.py
gita/utils.py
gita.egg-info/PKG-INFO
gita.egg-info/SOURCES.txt
gita.egg-info/dependency_links.txt
gita.egg-info/entry_points.txt
gita.egg-info/requires.txt
gita.egg-info/top_level.txt
tests/test_info.py
tests/test_main.py
tests/test_utils.py