Metadata-Version: 2.1
Name: gita
Version: 0.16.8.0
Summary: Manage multiple git repos with sanity
Home-page: https://github.com/nosarthur/gita
Author: Dong Zhou
Author-email: zhou.dong@gmail.com
License: MIT
Keywords: git,manage multiple repositories,cui,command-line
Platform: linux
Platform: osx
Platform: win32
Classifier: Development Status :: 4 - Beta
Classifier: Intended Audience :: Developers
Classifier: License :: OSI Approved :: MIT License
Classifier: Operating System :: POSIX
Classifier: Operating System :: MacOS :: MacOS X
Classifier: Operating System :: Microsoft :: Windows
Classifier: Topic :: Software Development :: Version Control :: Git
Classifier: Topic :: Terminals
Classifier: Topic :: Utilities
Classifier: Programming Language :: Python :: 3.8
Classifier: Programming Language :: Python :: 3.9
Classifier: Programming Language :: Python :: 3.10
Classifier: Programming Language :: Python :: 3.11
Classifier: Programming Language :: Python :: 3.12
Classifier: Programming Language :: Python :: 3.13
Classifier: Programming Language :: Python :: 3.14
Requires-Python: >=3.8
License-File: LICENSE
Requires-Dist: argcomplete
